cvtk.cpython-38-darwin.so
cvtk_release-0.0.6.dist-info/LICENSE
cvtk_release-0.0.6.dist-info/METADATA
cvtk_release-0.0.6.dist-info/WHEEL
cvtk_release-0.0.6.dist-info/top_level.txt
cvtk_release-0.0.6.dist-info/RECORD
