Metadata-Version: 2.1
Name: cvtk-release
Version: 0.0.6
Summary: CVTK, a Computer Vision ToolKit
Home-page: https://github.com/willard-yuan/cvtk-pypi
Author: Yong Yuan
Author-email: yongyuanstu@gmail.com
License: UNKNOWN
Platform: UNKNOWN
Requires-Python: >=3.6
License-File: LICENSE
Provides-Extra: test
Requires-Dist: pytest (>=6.0) ; extra == 'test'
